{"doc_id": "c1693a3edf7c5412", "source_path": "data/corpus/tier1_redistributable/AUSTRAC/Sign up for alerts.pdf", "jurisdiction": "Australia", "issuing_body": "AUSTRAC", "filename": "Sign up for alerts.pdf", "ext": "pdf", "extractor": "tesseract", "page_count": 2, "pages": [{"page": 1, "text": "26/06/2025, 17:31 Sign up for alerts | Cyber.gov.au\n\nSign up for alerts\n\nThis is a free service for Australian internet users providing information\non recent online threats and how they can be managed.\n\nThe Australian Signals Directorate’s Australian Cyber Security Centre (ASD's ACSC) Alert Service\nprovides easy-to-understand online security information and solutions to help protect internet\nusers at home, at work and on mobile devices. Our Alert Service also informs users about the\nlatest threats and vulnerabilities within an Australian context, and how to address risks to their\n\ndevices or computer networks.\nYou can see all our alerts and advisories.\n\nYou can also receive alerts by following us on our social channels on Facebook, Instagram,\n\nLinkedIn or X (formerly Twitter) or by bookmarking our alerts page in your web browser.\n\n@\n\nNever miss a threat\n\nSign up for the latest cyber security alerts and get information on threats and how to keep yourself secure\n\nonline.\n\nYour name\n\nee\n\nEmail\n\nns\n\nhttps://www.cyber.gov.au/about-us/register 1/2\n"}, {"page": 2, "text": "26/06/2025, 17:31 Sign up for alerts | Cyber.gov.au\n\nThis site is protected by reCAPTCHA and the Google Privacy Policy and Terms of Service apply.\n\n[ sonvororoers |\n\nhttps://www.cyber.gov.au/about-us/register 2/2\n"}], "extraction_errors": []}